[
  {
    "type": "git",
    "url": "https://go.googlesource.com/sys",
    "commit": "95e765b1cc43ac521bd4fd501e00774e34401449",
    "dest": "src/golang.org/x/sys"
  },
  {
    "type": "git",
    "url": "https://git.sr.ht/~avery/systray",
    "commit": "99b4d6c7eac2bf88a5c3700f258b3ad83fe2ec0b",
    "dest": "src/git.sr.ht/~avery/systray"
  },
  {
    "type": "git",
    "url": "https://git.sr.ht/~avery/crankshaft",
    "commit": "e8e69525d9a649fbd1759ee727f7a3baf33012da",
    "dest": "src/git.sr.ht/~avery/crankshaft"
  },
  {
    "type": "git",
    "url": "https://github.com/josharian/intern",
    "commit": "42b52b674af5a7cef9ce7e197bc21c78394ae65d",
    "dest": "src/github.com/josharian/intern"
  },
  {
    "type": "git",
    "url": "https://github.com/chromedp/chromedp",
    "commit": "6a8fef8d17ceaf7dd5d64ac614f207c9b7e9d15a",
    "dest": "src/github.com/chromedp/chromedp"
  },
  {
    "type": "git",
    "url": "https://github.com/chromedp/cdproto",
    "commit": "490dc4d81f7c42f18a08657e6f6084151460a2d1",
    "dest": "src/github.com/chromedp/cdproto"
  },
  {
    "type": "git",
    "url": "https://github.com/chromedp/sysutil",
    "commit": "dc95e7e83e8ace83d4f6dab60a16c539d2f25837",
    "dest": "src/github.com/chromedp/sysutil"
  },
  {
    "type": "git",
    "url": "https://github.com/gorilla/rpc",
    "commit": "27d3316e212c1acd2a8cb7d0df8a9173d974cbed",
    "dest": "src/github.com/gorilla/rpc"
  },
  {
    "type": "git",
    "url": "https://github.com/gorilla/websocket",
    "commit": "af47554f343b4675b30172ac301638d350db34a5",
    "dest": "src/github.com/gorilla/websocket"
  },
  {
    "type": "git",
    "url": "https://github.com/gorilla/handlers",
    "commit": "3e030244b4ba0480763356fc8ca0ade6222e2da0",
    "dest": "src/github.com/gorilla/handlers"
  },
  {
    "type": "git",
    "url": "https://github.com/adrg/xdg",
    "commit": "31e6a328d142d3b8ed43fda69c4f2b55e77d8e79",
    "dest": "src/github.com/adrg/xdg"
  },
  {
    "type": "git",
    "url": "https://github.com/mailru/easyjson",
    "commit": "a209843d8ea9db383ce1a1976e43c8e95f831c61",
    "dest": "src/github.com/mailru/easyjson"
  },
  {
    "type": "git",
    "url": "https://github.com/felixge/httpsnoop",
    "commit": "8b7a3718bcc5cce0a251b2d21eb77c58bcb1f788",
    "dest": "src/github.com/felixge/httpsnoop"
  },
  {
    "type": "git",
    "url": "https://github.com/boltdb/bolt",
    "commit": "fd01fc79c553a8e99d512a07e8e0c63d4a3ccfc5",
    "dest": "src/github.com/boltdb/bolt"
  },
  {
    "type": "git",
    "url": "https://github.com/gobwas/httphead",
    "commit": "935b70b38dcb69f249f00f338774bf75822c090a",
    "dest": "src/github.com/gobwas/httphead"
  },
  {
    "type": "git",
    "url": "https://github.com/gobwas/ws",
    "commit": "26e4a4444d77ecdf8a75215099f27cf941ce2db9",
    "dest": "src/github.com/gobwas/ws"
  },
  {
    "type": "git",
    "url": "https://github.com/gobwas/pool",
    "commit": "cd2fb0a117357da7830c32f332c8520db8e2827d",
    "dest": "src/github.com/gobwas/pool"
  },
  {
    "type": "git",
    "url": "https://github.com/evanw/esbuild",
    "commit": "46087213e4f9e8163dfae4d8568949a5ea1dc749",
    "dest": "src/github.com/evanw/esbuild"
  },
  {
    "type": "git",
    "url": "https://github.com/BurntSushi/toml",
    "commit": "1ba7f5b05951c7331f4eefea9bce295e2cb141f2",
    "dest": "src/github.com/BurntSushi/toml"
  }
]